[{"title":"Ímãs de neodímio n35 20 ~ 200 peças, bloco de imanes magnético permanente forte super forte 10*10*2 n35 ndfeb","code":"SYBR003566122"},{"title":"Fita de poliimida kapton, profissional, 30m, resistente ao calor, alta temperatura, isolamento eletrônico, solda industrial, 10 tamanhos, 1 peça","code":"BREDD6941728007YQ"},{"title":"Selo de rolo de proteção anti-roubo id selo manchar privacidade confidencial dados de proteção de dados ferramentas de bloqueador de endereço de identidade","code":"SY4651051511"}]